isbntools/__init__.py
isbntools/_conf.py
isbntools/_console.py
isbntools/_doitotex.py
isbntools/_exceptions.py
isbntools/_initapp.py
isbntools/_shelvecache.py
isbntools/app.py
isbntools/conf.py
isbntools/bin/__init__.py
isbntools/bin/classify.py
isbntools/bin/confc.py
isbntools/bin/cover.py
isbntools/bin/desc.py
isbntools/bin/doi.py
isbntools/bin/doi2tex.py
isbntools/bin/ean13.py
isbntools/bin/editions.py
isbntools/bin/from_words.py
isbntools/bin/goom.py
isbntools/bin/info.py
isbntools/bin/mask.py
isbntools/bin/meta.py
isbntools/bin/ren.py
isbntools/bin/repl.py
isbntools/bin/to_isbn10.py
isbntools/bin/to_isbn13.py
isbntools/bin/validate.py
isbntools/bin/version.py
isbntools/contrib/__init__.py
isbntools/contrib/apps/__init__.py
isbntools/contrib/modules/__init__.py
isbntools/contrib/modules/rename/__init__.py
isbntools/contrib/modules/rename/_rename.py
isbntools/contrib/modules/report/__init__.py
isbntools/contrib/modules/report/_audit.py
isbntools/contrib/modules/report/_columnize.py
isbntools/contrib/modules/report/_pypi.py
isbntools/contrib/modules/uxcolors/__init__.py
isbntools/contrib/modules/uxcolors/_colors.py
isbntools-4.3.29.data/data/isbntools/isbntools.conf
isbntools-4.3.29.dist-info/LICENSE-LGPL-3.0.txt
isbntools-4.3.29.dist-info/METADATA
isbntools-4.3.29.dist-info/WHEEL
isbntools-4.3.29.dist-info/entry_points.txt
isbntools-4.3.29.dist-info/top_level.txt
isbntools-4.3.29.dist-info/RECORD
