Metadata-Version: 2.1
Name: isbntools
Version: 4.3.29
Summary: app and framework for 'all things ISBN' (International Standard Book Number) including metadata, descriptions, covers... .
Home-page: https://github.com/xlcnd/isbntools
Author: Alexandre Lima Conde
Author-email: xlcnd@outlook.com
License: LGPL v3
Download-URL: https://github.com/xlcnd/isbntools/archive/v4.3.29.zip
Project-URL: Bug Reports, https://github.com/xlcnd/isbntools/issues
Project-URL: Dev Docs, https://github.com/xlcnd/isbntools/blob/dev/README.rst#info
Project-URL: Forum, https://stackoverflow.com/search?tab=newest&q=isbntools
Project-URL: License, https://github.com/xlcnd/isbntools/blob/dev/LICENSE-LGPL-3.0.txt
Keywords: ISBN metadata Google_Books Open_Library Wikipedia BibTeX EndNote RefWorks MSWord BibJSON ISBN-A doi
Platform: UNKNOWN
Classifier: Programming Language :: Python
Classifier: Programming Language :: Python :: 3
Classifier: Programming Language :: Python :: 3.5
Classifier: Programming Language :: Python :: 3.6
Classifier: Programming Language :: Python :: 3.7
Classifier: Programming Language :: Python :: 3.8
Classifier: Programming Language :: Python :: 3.9
Classifier: Programming Language :: Python :: 3.10
Classifier: License :: OSI Approved :: GNU Lesser General Public License v3 (LGPLv3)
Classifier: Operating System :: OS Independent
Classifier: Development Status :: 5 - Production/Stable
Classifier: Intended Audience :: End Users/Desktop
Classifier: Topic :: Text Processing :: General
Classifier: Topic :: Software Development :: Libraries :: Python Modules
